gwent/__init__.py
gwent/binary.py
gwent/detector.py
gwent/snr.py
gwent/snrplot.py
gwent/utils.py
gwent/waveform.py
gwent/LoadFiles/DiffStrain/EOBdiff/diff0002.dat
gwent/LoadFiles/DiffStrain/EOBdiff/diff0114.dat
gwent/LoadFiles/DiffStrain/EOBdiff/diff0178.dat
gwent/LoadFiles/DiffStrain/EOBdiff/diff0261.dat
gwent/LoadFiles/DiffStrain/EOBdiff/diff0303.dat
gwent/LoadFiles/InstrumentFiles/EinsteinTelescope/ET_B_data.txt
gwent/LoadFiles/InstrumentFiles/EinsteinTelescope/ET_C_data.txt
gwent/LoadFiles/InstrumentFiles/EinsteinTelescope/ET_D_data.txt
gwent/LoadFiles/InstrumentFiles/LISA_ESA/LISA_ESA_S_n_f_tot.txt
gwent/LoadFiles/InstrumentFiles/LISA_Other/LISA_Allocation_S_h.txt
gwent/LoadFiles/InstrumentFiles/LISA_Other/LISA_Allocation_S_h_tot.txt
gwent/LoadFiles/InstrumentFiles/LISA_Other/LISA_sensitivity.txt
gwent/LoadFiles/InstrumentFiles/LISA_Other/scg_3303.dat
gwent/LoadFiles/InstrumentFiles/LISA_Other/scg_6398.dat
gwent/LoadFiles/InstrumentFiles/LISA_Other/scg_6981.dat
gwent/LoadFiles/InstrumentFiles/NANOGrav/NANOGrav_11yr_params.txt
gwent/LoadFiles/InstrumentFiles/NANOGrav/StrainFiles/NANOGrav_11yr_S_eff.txt
gwent/LoadFiles/InstrumentFiles/NANOGrav/StrainFiles/cw_simulation_Ared_0_dp_0.5_fap_0.0001_T_15.txt
gwent/LoadFiles/InstrumentFiles/NANOGrav/StrainFiles/cw_simulation_Ared_0_dp_0.5_fap_0.0001_T_20.txt
gwent/LoadFiles/InstrumentFiles/NANOGrav/StrainFiles/cw_simulation_Ared_0_dp_0.5_fap_0.0001_T_25.txt
gwent/LoadFiles/InstrumentFiles/NANOGrav/StrainFiles/cw_simulation_Ared_0_dp_0.5_fap_0.001_T_15.txt
gwent/LoadFiles/InstrumentFiles/NANOGrav/StrainFiles/cw_simulation_Ared_0_dp_0.5_fap_0.001_T_20.txt
gwent/LoadFiles/InstrumentFiles/NANOGrav/StrainFiles/cw_simulation_Ared_0_dp_0.5_fap_0.001_T_25.txt
gwent/LoadFiles/InstrumentFiles/NANOGrav/StrainFiles/cw_simulation_Ared_0_dp_0.5_fap_0.003_T_15.txt
gwent/LoadFiles/InstrumentFiles/NANOGrav/StrainFiles/cw_simulation_Ared_0_dp_0.5_fap_0.003_T_20.txt
gwent-0.5.0.dist-info/AUTHORS.rst
gwent-0.5.0.dist-info/LICENSE
gwent-0.5.0.dist-info/METADATA
gwent-0.5.0.dist-info/WHEEL
gwent-0.5.0.dist-info/top_level.txt
gwent-0.5.0.dist-info/RECORD
