Metadata-Version: 2.1
Name: gwent
Version: 0.5.0
Summary: Gravitational Wave Detector Design Toolkit.
Home-page: https://github.com/ark0015/gwent
Author: Andrew Kaiser
Author-email: Andrew Kaiser <andrewkaiser70@gmail.com>
License: MIT license
Project-URL: Homepage, https://github.com/ark0015/gwent
Project-URL: Bug Tracker, https://github.com/ark0015/gwent/issues
Keywords: gwent
Classifier: Programming Language :: Python :: 3
Classifier: License :: OSI Approved :: MIT License
Classifier: Operating System :: OS Independent
Requires-Python: >=3.7
License-File: LICENSE
License-File: AUTHORS.rst
Requires-Dist: numpy
Requires-Dist: scipy
Requires-Dist: astropy
Requires-Dist: hasasia
Requires-Dist: matplotlib
Requires-Dist: h5py
Requires-Dist: pyyaml
Requires-Dist: lalsuite
Requires-Dist: gwinc
